{
    "max_depth": 5.0,
    "bbox": [
        [
            -0.449999839,
            -0.0113326581,
            -0.449999958
        ],
        [
            0.449999839,
            0.0113326581,
            0.450000018
        ]
    ],
    "origin": [
        -1.53502822,
        0.8862485,
        0.8662058
    ],
    "x_fov": 0.691150367,
    "y_fov": 0.691150367,
    "x": [
        -0.4999996,
        -0.8660256,
        -7.65249837E-08
    ],
    "y": [
        -0.380243778,
        0.2195337,
        -0.898454
    ],
    "z": [
        0.7780843,
        -0.449226618,
        -0.4390676
    ],
    "scale": [
        0.00449999841,
        0.00449999841,
        0.00449999841
    ],
    "offset": [
        0.450001419,
        -0.01133255,
        0.4500015
    ]
}
